{
	"name": "RunAt6AM",
	"properties": {
		"annotations": [],
		"runtimeState": "Started",
		"pipelines": [
			{
				"pipelineReference": {
					"referenceName": "DWScaleUpDown",
					"type": "PipelineReference"
				}
			}
		],
		"type": "ScheduleTrigger",
		"typeProperties": {
			"recurrence": {
				"frequency": "Day",
				"interval": 1,
				"startTime": "2021-05-01T06:00:00",
				"timeZone": "India Standard Time",
				"schedule": {
					"minutes": [
						0
					],
					"hours": [
						6
					]
				}
			}
		}
	}
}